{ "Example4_PyNN": {
    "notes": "A network for PyNN",
    "cells": [
        { "testcell": {
            "pynn_cell": "IF_cond_alpha",
            "parameters": {"tau_refrac": 5, "i_offset": 0.1} }
        },
        { "testcell2": {
            "pynn_cell": "IF_cond_alpha",
            "parameters": {"tau_refrac": 5, "i_offset": -0.1} }
        }
    ],
    "input_sources": [
        { "iclamp0": {
            "pynn_input": "DCSource",
            "parameters": {"start": 200.0, "stop": 800.0, "amplitude": 0.99} }
        }
    ],
    "populations": [
        { "pop0": {
            "component": "testcell",
            "size": 1 }
        },
        { "pop1": {
            "component": "testcell2",
            "size": 1 }
        }
    ],
    "projections": [
        { "proj0": {
            "synapse": "ampa",
            "weight": 0.02,
            "random_connectivity":                 { 
                    "probability": 1.0 },
            "presynaptic": "pop0",
            "delay": 2.0,
            "postsynaptic": "pop1" }
        }
    ],
    "inputs": [
        { "stim": {
            "input_source": "iclamp0",
            "percentage": 100.0,
            "population": "pop0" }
        }
    ] }
}